{
    "com.hutchind.cordova.plugins.launcher": {
        "source": {
            "type": "git",
            "url": "https://github.com/nchutchind/App-Launcher-Cordova-Plugin.git",
            "subdir": "."
        },
        "is_top_level": true,
        "variables": {}
    },
    "com.phonegap.plugins.nativesettingsopener": {
        "source": {
            "type": "git",
            "url": "https://github.com/deefactorial/Cordova-open-native-settings.git",
            "subdir": "."
        },
        "is_top_level": true,
        "variables": {}
    },
    "com.pylonproducts.wifiwizard": {
        "source": {
            "type": "registry",
            "id": "wifiwizard"
        },
        "is_top_level": true,
        "variables": {}
    }
}